{"timestamp":1757929468642,"version":"neural-v2.0","result":{"confidence":"Low","breakdown":{"transformer_score":22,"statistical_score":19,"feature_breakdown":{"ai_phrase_density":36,"sentence_uniformity":44.4,"vocabulary_complexity":82.7,"transition_density":14,"repetition_score":1},"neural_breakdown":{"perplexity_score":22,"coherence_score":32,"embedding_score":75,"style_score":100,"ensemble_score":45.9},"method":"Advanced Hybrid Neural + Statistical + Style Analysis"},"model_info":{"transformer_available":true,"model_name":"GPT-2 + SentenceTransformer + Statistical + Style","fallback_mode":false,"method":"Advanced Hybrid Detection v2.0"},"processing_time":633,"wordCount":197,"textLength":1240,"totalProcessingTime":14832,"cached":false,"aiProbability":55,"geminiScore":75},"metadata":{"wordCount":197,"confidence":"Low","processingTime":14832,"neuralAvailable":true}}